charts_dashboard/__init__.py
charts_dashboard/admin.py
charts_dashboard/apps.py
charts_dashboard/mixins.py
charts_dashboard/objects.py
charts_dashboard/views.py
charts_dashboard/templatetags/__init__.py
charts_dashboard/templatetags/charts.py
tests/__init__.py
tests/test_settings.py
tests/tests.py
tests/urls.py
django_charts_dashboard-0.1.dist-info/AUTHORS.rst
django_charts_dashboard-0.1.dist-info/LICENSE
django_charts_dashboard-0.1.dist-info/METADATA
django_charts_dashboard-0.1.dist-info/WHEEL
django_charts_dashboard-0.1.dist-info/top_level.txt
django_charts_dashboard-0.1.dist-info/RECORD
